[
  {
    "character_id": "ayloc",
    "created_at": "2026-03-05T04:12:32Z",
    "id": "bag-of-holding",
    "location": "",
    "mount_id": null,
    "name": "Bag of Holding",
    "notes": "",
    "type": "bag",
    "updated_at": "2026-03-05T04:12:32Z",
    "version": 1,
    "weight_limit": null
  },
  {
    "character_id": "andurin",
    "created_at": "2026-03-05T04:12:32Z",
    "id": "andurin",
    "location": "",
    "mount_id": null,
    "name": "Andurin",
    "notes": "",
    "type": "character",
    "updated_at": "2026-03-05T04:12:32Z",
    "version": 1,
    "weight_limit": null
  },
  {
    "character_id": "ayloc",
    "created_at": "2026-03-05T04:12:32Z",
    "id": "ayloc",
    "location": "",
    "mount_id": null,
    "name": "Ayloc",
    "notes": "",
    "type": "character",
    "updated_at": "2026-03-05T04:12:32Z",
    "version": 1,
    "weight_limit": null
  },
  {
    "character_id": "ruya",
    "created_at": "2026-03-05T04:12:32Z",
    "id": "ruya",
    "location": "",
    "mount_id": null,
    "name": "Rüya",
    "notes": "",
    "type": "character",
    "updated_at": "2026-03-05T04:12:32Z",
    "version": 1,
    "weight_limit": null
  },
  {
    "character_id": "sachan",
    "created_at": "2026-03-05T04:12:32Z",
    "id": "sachan",
    "location": "",
    "mount_id": null,
    "name": "Sachan",
    "notes": "",
    "type": "character",
    "updated_at": "2026-03-05T04:12:32Z",
    "version": 1,
    "weight_limit": null
  },
  {
    "character_id": "ingvild",
    "created_at": "2026-03-05T04:12:32Z",
    "id": "ingvild",
    "location": "",
    "mount_id": null,
    "name": "Ingvild",
    "notes": "",
    "type": "character",
    "updated_at": "2026-03-05T04:12:32Z",
    "version": 1,
    "weight_limit": null
  },
  {
    "character_id": "hrothgar",
    "created_at": "2026-03-05T04:12:32Z",
    "id": "hrothgar",
    "location": "",
    "mount_id": null,
    "name": "Hrothgar",
    "notes": "",
    "type": "character",
    "updated_at": "2026-03-05T04:12:32Z",
    "version": 1,
    "weight_limit": null
  },
  {
    "character_id": null,
    "created_at": "2026-03-05T04:12:32Z",
    "id": "cached",
    "location": "",
    "mount_id": null,
    "name": "Cached/Stored",
    "notes": "",
    "type": "cache",
    "updated_at": "2026-03-05T04:12:32Z",
    "version": 1,
    "weight_limit": null
  },
  {
    "character_id": "sachan",
    "created_at": "2026-03-05T04:12:32Z",
    "id": "quiver-of-sylvana",
    "location": "",
    "mount_id": null,
    "name": "Quiver of Sylvana",
    "notes": "",
    "type": "bag",
    "updated_at": "2026-03-05T04:12:32Z",
    "version": 1,
    "weight_limit": null
  },
  {
    "character_id": null,
    "created_at": "2026-03-05T04:12:32Z",
    "id": "bill-the-mule",
    "location": "",
    "mount_id": null,
    "name": "Bill the Mule",
    "notes": "",
    "type": "mount",
    "updated_at": "2026-03-05T04:12:32Z",
    "version": 1,
    "weight_limit": null
  }
]